Workbook

Sheet Dashboard
A1: 📊 لوحة التحكم — 3D Makers Dashboard
A2: شراكة محمد (رأس المال) & نبيل (التشغيل والتسويق)
A4: 💰 رأس المال / Capital
B5: إجمالي رأس المال المُستثمر | C5: =Capital!D103
B6: ثمن الطابعة ثلاثية الأبعاد | C6: =Capital!D3
A8: 🛒 الإيرادات والمبيعات / Revenue & Sales
B9: إجمالي الإيرادات حتى الآن | C9: =Sales!E203
B10: عدد القطع المباعة | C10: =Sales!C203
B11: متوسط سعر البيع لكل قطعة | C11: =IFERROR(Sales!E203/Sales!C203,0)
A13: 📦 التكاليف / Costs
B14: إجمالي مصاريف المواد (المشتريات) | C14: =Purchases!D203
B15: إجمالي المصاريف العامة (التشغيلية) | C15: =Expenses!D203
B16: إجمالي مصاريف الإعلانات | C16: =Advertising!E103
B17: إجمالي التكاليف التشغيلية | C17: =Purchases!D203+Expenses!D203+Advertising!E103
B18: متوسط تكلفة الإنتاج لكل قطعة | C18: =IFERROR(AVERAGEIF(ProductCalc!G7:G56,">0"),0)
A20: 📈 الربح / Profit
B21: صافي الربح الإجمالي | C21: =Sales!E203-Purchases!D203-Expenses!D203-Advertising!E103
B22: نسبة هامش الربح الإجمالي | C22: =IFERROR((Sales!E203-Purchases!D203-Expenses!D203-Advertising!E103)/Sales!E203,0)
A24: 🖨️ استرداد رأس المال / Capital Recovery
B25: الربح المتراكم (للاسترداد) | C25: =Sales!E203-Purchases!D203-Expenses!D203-Advertising!E103
B26: المبلغ المتبقي لاسترداد رأس المال | C26: =MAX(Capital!D103-(Sales!E203-Purchases!D203-Expenses!D203-Advertising!E103),0)
B27: هل تم استرداد رأس المال؟ | C27: =IF((Sales!E203-Purchases!D203-Expenses!D203-Advertising!E103)>=Capital!D103,"✅ نعم — تم الاسترداد","❌ لا — لم يتم بعد")
B28: نسبة الاسترداد | C28: =IFERROR((Sales!E203-Purchases!D203-Expenses!D203-Advertising!E103)/Capital!D103,0)

Sheet Capital
A1: رأس المال — Capital Investments
A2: التاريخ Date | B2: نوع الاستثمار Investment Type | C2: الوصف Description | D2: المبلغ ($) Amount | E2: ملاحظات Notes
A3: 45672 | B3: طابعة ثلاثية الأبعاد | C3: Creality Ender 3 V3 SE | D3: 250 | E3: الدفعة الأولى — ثمن الطابعة كاملاً
A4: 45689 | B4: موقع إلكتروني / منصة | C4: بناء واستضافة المتجر الإلكتروني | D4: 150 | E4: تصميم + استضافة سنة
A5: 45698 | B5: معدات وأدوات | C5: أدوات تشطيب + مواد تغليف | D5: 35 | E5: مقص حراري + ورق صنفرة + أكياس
A103: الإجمالي / Total | D103: =SUM(D3:D102)

Sheet ProductCalc
A1: حاسبة التكلفة والسعر — Product Cost Calculator
A2: الافتراضات / Assumptions
A3: سعر الفيلمنت لكل غرام ($) | B3: 0.015 | D3: 🟨 الخلايا الصفراء = قيم قابلة للتعديل
A4: تكلفة الطابعة لكل ساعة ($) | B4: 0.3 | D4: جميع الصيغ مرتبطة بهذه الخانتين تلقائياً
A6: اسم المنتج Product Name | B6: وزن الفيلمنت (غرام) Filament (g) | C6: تكلفة الفيلمنت ($) Filament Cost | D6: وقت الطباعة (ساعة) Print Time (h) | E6: تكلفة التشغيل ($) Printer Cost | F6: مواد إضافية ($) Extra Materials | G6: إجمالي التكلفة ($) Total Cost | H6: هامش الربح المرغوب % Desired Margin | I6: سعر البيع المقترح ($) Suggested Price | J6: سعر البيع الفعلي ($) Actual Price | K6: الربح الفعلي ($) Actual Profit | L6: هامش الربح الفعلي % Actual Margin
A7: علاقة مفاتيح — Keychain | B7: 25 | C7: =IF(B7="","",B7*$B$3) | D7: 1.5 | E7: =IF(D7="","",D7*$B$4) | F7: 0.2 | G7: =IF(B7="","",C7+E7+IF(F7="",0,F7)) | H7: 0.5 | I7: =IF(G7="","",G7*(1+IF(H7="",0,H7))) | J7: 2.5 | K7: =IF(J7="","",J7-G7) | L7: =IFERROR(K7/J7,"")
A8: مجسم ديكور صغير — Figurine | B8: 80 | C8: =IF(B8="","",B8*$B$3) | D8: 4 | E8: =IF(D8="","",D8*$B$4) | F8: 0.5 | G8: =IF(B8="","",C8+E8+IF(F8="",0,F8)) | H8: 0.6 | I8: =IF(G8="","",G8*(1+IF(H8="",0,H8))) | J8: 8 | K8: =IF(J8="","",J8-G8) | L8: =IFERROR(K8/J8,"")
A9: حامل موبايل — Phone Stand | B9: 120 | C9: =IF(B9="","",B9*$B$3) | D9: 5 | E9: =IF(D9="","",D9*$B$4) | F9: 0.5 | G9: =IF(B9="","",C9+E9+IF(F9="",0,F9)) | H9: 0.4 | I9: =IF(G9="","",G9*(1+IF(H9="",0,H9))) | J9: 10 | K9: =IF(J9="","",J9-G9) | L9: =IFERROR(K9/J9,"")
C10: =IF(B10="","",B10*$B$3) | E10: =IF(D10="","",D10*$B$4) | G10: =IF(B10="","",C10+E10+IF(F10="",0,F10)) | I10: =IF(G10="","",G10*(1+IF(H10="",0,H10))) | K10: =IF(J10="","",J10-G10) | L10: =IFERROR(K10/J10,"")
C11: =IF(B11="","",B11*$B$3) | E11: =IF(D11="","",D11*$B$4) | G11: =IF(B11="","",C11+E11+IF(F11="",0,F11)) | I11: =IF(G11="","",G11*(1+IF(H11="",0,H11))) | K11: =IF(J11="","",J11-G11) | L11: =IFERROR(K11/J11,"")
C12: =IF(B12="","",B12*$B$3) | E12: =IF(D12="","",D12*$B$4) | G12: =IF(B12="","",C12+E12+IF(F12="",0,F12)) | I12: =IF(G12="","",G12*(1+IF(H12="",0,H12))) | K12: =IF(J12="","",J12-G12) | L12: =IFERROR(K12/J12,"")
C13: =IF(B13="","",B13*$B$3) | E13: =IF(D13="","",D13*$B$4) | G13: =IF(B13="","",C13+E13+IF(F13="",0,F13)) | I13: =IF(G13="","",G13*(1+IF(H13="",0,H13))) | K13: =IF(J13="","",J13-G13) | L13: =IFERROR(K13/J13,"")
C14: =IF(B14="","",B14*$B$3) | E14: =IF(D14="","",D14*$B$4) | G14: =IF(B14="","",C14+E14+IF(F14="",0,F14)) | I14: =IF(G14="","",G14*(1+IF(H14="",0,H14))) | K14: =IF(J14="","",J14-G14) | L14: =IFERROR(K14/J14,"")
C15: =IF(B15="","",B15*$B$3) | E15: =IF(D15="","",D15*$B$4) | G15: =IF(B15="","",C15+E15+IF(F15="",0,F15)) | I15: =IF(G15="","",G15*(1+IF(H15="",0,H15))) | K15: =IF(J15="","",J15-G15) | L15: =IFERROR(K15/J15,"")
C16: =IF(B16="","",B16*$B$3) | E16: =IF(D16="","",D16*$B$4) | G16: =IF(B16="","",C16+E16+IF(F16="",0,F16)) | I16: =IF(G16="","",G16*(1+IF(H16="",0,H16))) | K16: =IF(J16="","",J16-G16) | L16: =IFERROR(K16/J16,"")
C17: =IF(B17="","",B17*$B$3) | E17: =IF(D17="","",D17*$B$4) | G17: =IF(B17="","",C17+E17+IF(F17="",0,F17)) | I17: =IF(G17="","",G17*(1+IF(H17="",0,H17))) | K17: =IF(J17="","",J17-G17) | L17: =IFERROR(K17/J17,"")
C18: =IF(B18="","",B18*$B$3) | E18: =IF(D18="","",D18*$B$4) | G18: =IF(B18="","",C18+E18+IF(F18="",0,F18)) | I18: =IF(G18="","",G18*(1+IF(H18="",0,H18))) | K18: =IF(J18="","",J18-G18) | L18: =IFERROR(K18/J18,"")
C19: =IF(B19="","",B19*$B$3) | E19: =IF(D19="","",D19*$B$4) | G19: =IF(B19="","",C19+E19+IF(F19="",0,F19)) | I19: =IF(G19="","",G19*(1+IF(H19="",0,H19))) | K19: =IF(J19="","",J19-G19) | L19: =IFERROR(K19/J19,"")
C20: =IF(B20="","",B20*$B$3) | E20: =IF(D20="","",D20*$B$4) | G20: =IF(B20="","",C20+E20+IF(F20="",0,F20)) | I20: =IF(G20="","",G20*(1+IF(H20="",0,H20))) | K20: =IF(J20="","",J20-G20) | L20: =IFERROR(K20/J20,"")
C21: =IF(B21="","",B21*$B$3) | E21: =IF(D21="","",D21*$B$4) | G21: =IF(B21="","",C21+E21+IF(F21="",0,F21)) | I21: =IF(G21="","",G21*(1+IF(H21="",0,H21))) | K21: =IF(J21="","",J21-G21) | L21: =IFERROR(K21/J21,"")
... C56: =IF(B56="","",B56*$B$3) | E56: =IF(D56="","",D56*$B$4) | G56: =IF(B56="","",C56+E56+IF(F56="",0,F56)) | I56: =IF(G56="","",G56*(1+IF(H56="",0,H56))) | K56: =IF(J56="","",J56-G56) | L56: =IFERROR(K56/J56,"")

Sheet Purchases
A1: سجل المشتريات — Purchases Log
A2: التاريخ Date | B2: نوع المادة Material | C2: الكمية (غرام/وحدة) Quantity | D2: السعر الإجمالي ($) Total Price | E2: سعر الوحدة ($) Unit Price | F2: المورّد Supplier | G2: ملاحظات Notes
A3: 45703 | B3: فيلمنت PLA — أبيض | C3: 1000 | D3: 15 | E3: =IFERROR(D3/C3,"") | F3: Amazon | G3: أول كمية — 1 كيلو
A4: 45717 | B4: فيلمنت PLA — أسود | C4: 1000 | D4: 15 | E4: =IFERROR(D4/C4,"") | F4: Amazon | G4: كيلو ثاني
E5: =IFERROR(D5/C5,"")
E6: =IFERROR(D6/C6,"")
E7: =IFERROR(D7/C7,"")
E8: =IFERROR(D8/C8,"")
E9: =IFERROR(D9/C9,"")
E10: =IFERROR(D10/C10,"")
E11: =IFERROR(D11/C11,"")
E12: =IFERROR(D12/C12,"")
E13: =IFERROR(D13/C13,"")
E14: =IFERROR(D14/C14,"")
E15: =IFERROR(D15/C15,"")
E16: =IFERROR(D16/C16,"")
... E202: =IFERROR(D202/C202,"")
A203: إجمالي مصاريف المواد / Total | D203: =SUM(D3:D202)

Sheet Sales
A1: سجل المبيعات — Sales Log
A2: التاريخ Date | B2: اسم المنتج Product | C2: الكمية Quantity | D2: سعر البيع للوحدة ($) Unit Price | E2: الإجمالي ($) Total | F2: قناة البيع Sales Channel | G2: ملاحظات Notes
A3: 45721 | B3: علاقة مفاتيح — Keychain | C3: 3 | D3: 2.5 | E3: =IF(C3="","",C3*D3) | F3: واتساب | G3: أول طلبية!
A4: 45726 | B4: حامل موبايل — Phone Stand | C4: 1 | D4: 10 | E4: =IF(C4="","",C4*D4) | F4: يد بيد | G4: بيع مباشر لصديق
E5: =IF(C5="","",C5*D5)
E6: =IF(C6="","",C6*D6)
E7: =IF(C7="","",C7*D7)
E8: =IF(C8="","",C8*D8)
E9: =IF(C9="","",C9*D9)
E10: =IF(C10="","",C10*D10)
E11: =IF(C11="","",C11*D11)
E12: =IF(C12="","",C12*D12)
E13: =IF(C13="","",C13*D13)
E14: =IF(C14="","",C14*D14)
E15: =IF(C15="","",C15*D15)
E16: =IF(C16="","",C16*D16)
... E202: =IF(C202="","",C202*D202)
A203: إجمالي الإيرادات / Total Revenue | C203: =SUM(C3:C202) | E203: =SUM(E3:E202)
A204: إجمالي عدد الوحدات المباعة / Total Units | C204: =SUM(C3:C202)

Sheet Expenses
A1: المصاريف العامة — General Expenses
A2: التاريخ Date | B2: الفئة Category | C2: الوصف Description | D2: المبلغ ($) Amount | E2: ملاحظات Notes
A3: 45717 | B3: اشتراكات وخدمات رقمية | C3: اشتراك Canva Pro شهري | D3: 12.99 | E3: لتصميم منشورات السوشال ميديا
A4: 45731 | B4: نقل وتوصيل | C4: توصيل طلبية للعميل | D4: 5
A203: إجمالي المصاريف / Total | D203: =SUM(D3:D202)

Sheet Advertising
A1: سجل الإعلانات — Advertising Log
A2: التاريخ Date | B2: المنصة Platform | C2: نوع الحملة Campaign Type | D2: الميزانية المخصصة ($) Budget | E2: المبلغ الفعلي ($) Actual Spend | F2: عدد المبيعات الناتجة Sales Count | G2: الإيراد الناتج ($) Revenue | H2: العائد على الإعلان ROAS | I2: ملاحظات Notes
A3: 45748 | B3: Instagram | C3: ترويج منشور — Boost Post | D3: 20 | E3: 18.5 | F3: 4 | G3: 35 | H3: =IFERROR(G3/E3,"") | I3: أول حملة تجريبية
H4: =IFERROR(G4/E4,"")
H5: =IFERROR(G5/E5,"")
H6: =IFERROR(G6/E6,"")
H7: =IFERROR(G7/E7,"")
H8: =IFERROR(G8/E8,"")
H9: =IFERROR(G9/E9,"")
H10: =IFERROR(G10/E10,"")
H11: =IFERROR(G11/E11,"")
H12: =IFERROR(G12/E12,"")
H13: =IFERROR(G13/E13,"")
H14: =IFERROR(G14/E14,"")
H15: =IFERROR(G15/E15,"")
... H102: =IFERROR(G102/E102,"")
A103: إجمالي مصاريف الإعلانات / Total Ad Spend | E103: =SUM(E3:E102) | G103: =SUM(G3:G102)
A104: متوسط ROAS / Average ROAS | H104: =IFERROR(SUM(G3:G102)/SUM(E3:E102),0)
